robo_log/__init__.py
robo_log/_ast_utils.py
robo_log/_auto_logging_setup.py
robo_log/_config.py
robo_log/_convert_units.py
robo_log/_decoder.py
robo_log/_index.py
robo_log/_index_v2.py
robo_log/_lifecycle_hooks.py
robo_log/_logger_instances.py
robo_log/_obj_info_repr.py
robo_log/_rewrite_ast_add_callbacks.py
robo_log/_rewrite_filtering.py
robo_log/_rewrite_importhook.py
robo_log/_robo_logger.py
robo_log/_robo_output_impl.py
robo_log/protocols.py
robo_log/py.typed
robocorp_logging-0.0.9.dist-info/LICENSE
robocorp_logging-0.0.9.dist-info/METADATA
robocorp_logging-0.0.9.dist-info/WHEEL
robocorp_logging-0.0.9.dist-info/RECORD
