Metadata-Version: 2.1
Name: robocorp-logging
Version: 0.0.9
Summary: Automatic trace logging for Python
Author: Fabio Z.
Author-email: fabio@robocorp.com
Requires-Python: >=3.9,<4.0
Classifier: Programming Language :: Python :: 3
Classifier: Programming Language :: Python :: 3.9
Classifier: Programming Language :: Python :: 3.10
Classifier: Programming Language :: Python :: 3.11
Requires-Dist: tomli (>=2.0.1,<3.0.0) ; python_version < "3.11"
